python_utilities/__init__.py
python_utilities/config_util.py
python_utilities/list_util.py
python_utilities/log_util.py
python_utilities/pyqt_util.py
python_utilities/reflection_util.py
python_utilities/schedule_util.py
python_utilities/string_util.py
python_utilities/thread_util.py
python_utilities/unit_conversion.py
python_utilities/os_util/__init__.py
python_utilities/os_util/archive.py
python_utilities/os_util/command.py
python_utilities/os_util/exceptions.py
python_utilities/os_util/file.py
python_utilities/os_util/path.py
python_utilities/os_util/serialization.py
python_utilities/os_util/system.py
python_utilities-1.0.22.dist-info/DESCRIPTION.rst
python_utilities-1.0.22.dist-info/METADATA
python_utilities-1.0.22.dist-info/RECORD
python_utilities-1.0.22.dist-info/WHEEL
python_utilities-1.0.22.dist-info/metadata.json
python_utilities-1.0.22.dist-info/top_level.txt
