Metadata-Version: 2.0
Name: python-utilities
Version: 1.0.22
Summary: A set of simple utility APIs for higher-level python functions.
Home-page: https://github.com/TheKewlStore/PythonUtilities
Author: Ian Davis
Author-email: thekewlstore@gmail.com
License: UNKNOWN
Platform: UNKNOWN
Requires-Dist: colorlog
